coda/__init__.py
coda/__version__.py
coda/apps/cli/__init__.py
coda/apps/cli/agent_chat.py
coda/apps/cli/agent_event_handler.py
coda/apps/cli/banner.py
coda/apps/cli/cli.py
coda/apps/cli/command_registry.py
coda/apps/cli/completers.py
coda/apps/cli/completion_selector.py
coda/apps/cli/constants.py
coda/apps/cli/error_handler.py
coda/apps/cli/generic_command_selector.py
coda/apps/cli/interactive.py
coda/apps/cli/interactive_cli.py
coda/apps/cli/interfaces.py
coda/apps/cli/main.py
coda/apps/cli/provider_manager.py
coda/apps/cli/search_display.py
coda/apps/cli/session_commands.py
coda/apps/cli/tool_chat.py
coda/apps/cli/utils.py
coda/apps/cli/web_command.py
coda/apps/cli/commands/__init__.py
coda/apps/cli/commands/mcp_commands.py
coda/apps/cli/commands/session_commands.py
coda/apps/cli/shared/__init__.py
coda/apps/cli/shared/commands.py
coda/apps/cli/shared/help.py
coda/apps/cli/shared/modes.py
coda/apps/web/__init__.py
coda/apps/web/agent_event_handler.py
coda/apps/web/app.py
coda/apps/web/app_minimal.py
coda/apps/web/app_simple.py
coda/apps/web/components/__init__.py
coda/apps/web/components/chat_widget.py
coda/apps/web/components/file_manager.py
coda/apps/web/components/model_selector.py
coda/apps/web/components/tool_settings.py
coda/apps/web/pages/__init__.py
coda/apps/web/pages/chat.py
coda/apps/web/pages/dashboard.py
coda/apps/web/pages/sessions.py
coda/apps/web/pages/settings.py
coda/apps/web/services/__init__.py
coda/apps/web/services/agent_service.py
coda/apps/web/utils/__init__.py
coda/apps/web/utils/state.py
coda/base/README.md
coda/base/__init__.py
coda/base/config/README.md
coda/base/config/__init__.py
coda/base/config/constants.py
coda/base/config/example.py
coda/base/config/manager.py
coda/base/config/models.py
coda/base/observability/README.md
coda/base/observability/__init__.py
coda/base/observability/base.py
coda/base/observability/collections.py
coda/base/observability/commands.py
coda/base/observability/constants.py
coda_code_assistant-2025.8.22.910.dist-info/METADATA
coda_code_assistant-2025.8.22.910.dist-info/WHEEL
coda_code_assistant-2025.8.22.910.dist-info/entry_points.txt
coda_code_assistant-2025.8.22.910.dist-info/licenses/LICENSE
coda_code_assistant-2025.8.22.910.dist-info/RECORD
