Metadata-Version: 2.4
Name: coda-code-assistant
Version: 2025.8.22.910
Summary: A CLI-focused code assistant for AI-assisted development
License-File: LICENSE
Requires-Python: >=3.11
Requires-Dist: aiosqlite>=0.19.0
Requires-Dist: chromadb>=0.4.0
Requires-Dist: click>=8.0.0
Requires-Dist: cryptography>=3.4.7
Requires-Dist: diagram-renderer>=2025.8.3.1111
Requires-Dist: faiss-cpu>=1.7.4
Requires-Dist: grep-ast>=0.9.0
Requires-Dist: httpx>=0.25.0
Requires-Dist: litellm>=1.0.0
Requires-Dist: mcp>=1.0.0
Requires-Dist: numpy>=1.24.0
Requires-Dist: oci>=2.119.1
Requires-Dist: opentelemetry-api>=1.20.0
Requires-Dist: opentelemetry-exporter-otlp>=1.20.0
Requires-Dist: opentelemetry-instrumentation>=0.41b0
Requires-Dist: opentelemetry-sdk>=1.20.0
Requires-Dist: pandas>=2.0.0
Requires-Dist: plotly>=5.0.0
Requires-Dist: prompt-toolkit>=3.0.0
Requires-Dist: pydantic>=2.0.0
Requires-Dist: pygments>=2.19.2
Requires-Dist: pyyaml>=6.0.1
Requires-Dist: requests>=2.32.4
Requires-Dist: rich>=13.0.0
Requires-Dist: sentence-transformers>=2.2.0
Requires-Dist: sqlalchemy>=2.0.0
Requires-Dist: streamlit-ace>=0.1.1
Requires-Dist: streamlit>=1.40.0
Requires-Dist: tiktoken>=0.5.0
Requires-Dist: tomli-w>=1.2.0
Requires-Dist: tomlkit>=0.12.0
Requires-Dist: tree-sitter-language-pack>=0.8.0
Provides-Extra: dev
Requires-Dist: black>=23.0.0; extra == 'dev'
Requires-Dist: mypy>=1.0.0; extra == 'dev'
Requires-Dist: pexpect>=4.8.0; extra == 'dev'
Requires-Dist: pre-commit>=3.5.0; extra == 'dev'
Requires-Dist: pytest-asyncio<1.0,>=0.21.0; extra == 'dev'
Requires-Dist: pytest-cov>=4.0.0; extra == 'dev'
Requires-Dist: pytest>=8.0.0; extra == 'dev'
Requires-Dist: ruff>=0.1.0; extra == 'dev'
Provides-Extra: oracle
Requires-Dist: oracledb>=2.0.0; extra == 'oracle'
Provides-Extra: performance
Requires-Dist: locust>=2.0.0; extra == 'performance'
Requires-Dist: pytest-benchmark>=4.0.0; extra == 'performance'
Provides-Extra: test-web
Requires-Dist: pytest-asyncio>=0.21.0; extra == 'test-web'
Requires-Dist: pytest-cov>=4.0.0; extra == 'test-web'
Requires-Dist: pytest-selenium>=4.0.0; extra == 'test-web'
Requires-Dist: pytest-timeout>=2.0.0; extra == 'test-web'
Requires-Dist: pytest>=8.0.0; extra == 'test-web'
Requires-Dist: requests>=2.32.0; extra == 'test-web'
Requires-Dist: selenium>=4.0.0; extra == 'test-web'
